pytext/__init__.py
fb_pytext-0.1.dist-info/LICENSE
fb_pytext-0.1.dist-info/METADATA
fb_pytext-0.1.dist-info/WHEEL
fb_pytext-0.1.dist-info/top_level.txt
fb_pytext-0.1.dist-info/RECORD
