Metadata-Version: 2.1
Name: fb-pytext
Version: 0.1
Summary: pytorch modeling framework and model zoo for text models
Home-page: UNKNOWN
Author: Facebook
Author-email: snisarg@fb.com
License: BSD
Platform: UNKNOWN
